Github/Search.py
Github/Timer.py
Github/Utils.py
Github/Version.py
Github/__init__.py
Github/__main__.py
github_search_cli-0.4.dist-info/LICENSE
github_search_cli-0.4.dist-info/METADATA
github_search_cli-0.4.dist-info/WHEEL
github_search_cli-0.4.dist-info/entry_points.txt
github_search_cli-0.4.dist-info/top_level.txt
github_search_cli-0.4.dist-info/RECORD
